gummy/__init__.py
gummy/cli/check_driver.py
gummy/cli/translate_journal.py
gummy/cli/translate_text.py
gummy/gateways.py
gummy/journals.py
gummy/models.py
gummy/templates/base.html
gummy/templates/components/corr_translation.html
gummy/templates/header.html
gummy/templates/paper.html
gummy/templates/style.css
gummy/templates/style.less
gummy/translators.py
gummy/utils/__init__.py
gummy/utils/_data.py
gummy/utils/_exceptions.py
gummy/utils/_path.py
gummy/utils/_type.py
gummy/utils/_warnings.py
gummy/utils/coloring_utils.py
gummy/utils/compress_utils.py
gummy/utils/download_utils.py
gummy/utils/driver_utils.py
gummy/utils/environ_utils.py
gummy/utils/generic_utils.py
gummy/utils/journal_utils.py
gummy/utils/monitor_utils.py
gummy/utils/outfmt_utils.py
gummy/utils/pdf_utils.py
gummy/utils/soup_utils.py
gummy/utils/templates.py
translation_gummy-4.0.1.dist-info/entry_points.txt
translation_gummy-4.0.1.dist-info/LICENSE
translation_gummy-4.0.1.dist-info/WHEEL
translation_gummy-4.0.1.dist-info/METADATA
translation_gummy-4.0.1.dist-info/RECORD
