Metadata-Version: 2.1
Name: translation-gummy
Version: 4.0.1
Summary: Translation Gummy is a magical gadget which enables user to be able to speak and understand other languages.
Home-page: https://iwasakishuto.github.io/Translation-Gummy/index.html
License: MIT
Author: iwasakishuto
Author-email: cabernet.rock@gmail.com
Requires-Python: >=3.8,<4.0
Classifier: Development Status :: 5 - Production/Stable
Classifier: Environment :: Console
Classifier: Intended Audience :: Other Audience
Classifier: License :: OSI Approved :: MIT License
Classifier: Programming Language :: Python :: 3
Classifier: Programming Language :: Python :: 3.10
Classifier: Programming Language :: Python :: 3.6
Classifier: Programming Language :: Python :: 3.7
Classifier: Programming Language :: Python :: 3.8
Classifier: Programming Language :: Python :: 3.9
Classifier: Topic :: Software Development :: Libraries
Classifier: Topic :: Software Development :: Libraries :: Python Modules
Provides-Extra: windows
Requires-Dist: Jinja2 (>=3.1.1,<4.0.0)
Requires-Dist: MarkupSafe (>=2.0.1,<3.0.0)
Requires-Dist: PyPDF2 (>=1.27.3,<2.0.0)
Requires-Dist: Werkzeug (>=1.0.1,<2.0.0)
Requires-Dist: beautifulsoup4 (>=4.11.1,<5.0.0)
Requires-Dist: html5lib (>=1.1,<2.0)
Requires-Dist: lxml (>=4.6.3,<5.0.0)
Requires-Dist: nltk (>=3.6.2,<4.0.0)
Requires-Dist: pdfkit (>=0.6.1,<0.7.0)
Requires-Dist: pdfminer (>=20191125,<20191126)
Requires-Dist: pylatexenc (>=2.10,<3.0)
Requires-Dist: python-dotenv (>=0.17.1,<0.18.0)
Requires-Dist: python-magic (>=0.4.22,<0.5.0)
Requires-Dist: requests (>=2.27.1,<3.0.0)
Requires-Dist: selenium (>=4.1.3,<5.0.0)
Requires-Dist: undetected-chromedriver (>=3.1.5,<4.0.0)
Project-URL: Bug Reports, https://github.com/iwasakishuto/Translation-Gummy/issues
Project-URL: Documentation, https://iwasakishuto.github.io/Translation-Gummy/index.html
Project-URL: Repository, https://github.com/iwasakishuto/Translation-Gummy
Project-URL: Source Code, https://github.com/iwasakishuto/Translation-Gummy
Project-URL: Say Thanks!, https://twitter.com/cabernet_rock
